image_grid_mark/__init__.py
image_grid_mark/__main__.py
image_grid_mark/main.py
image_grid_mark/resource_manager.py
image_grid_mark/tk_inf.py
image_grid_mark/assets/ico.png
image_grid_mark-0.0.1.dist-info/licenses/LICENSE
image_grid_mark-0.0.1.dist-info/METADATA
image_grid_mark-0.0.1.dist-info/WHEEL
image_grid_mark-0.0.1.dist-info/entry_points.txt
image_grid_mark-0.0.1.dist-info/top_level.txt
image_grid_mark-0.0.1.dist-info/RECORD
