Metadata-Version: 2.4
Name: image_grid_mark
Version: 0.0.1
Summary: gui for smalk krypto testing .
Author-email: The220th <The220th@gmail.com>
License-Expression: MIT
Project-URL: Homepage, https://github.com/The220th/image_grid_mark
Project-URL: Issues, https://github.com/The220th/image_grid_mark/issues
Classifier: Programming Language :: Python :: 3
Classifier: Operating System :: POSIX :: Linux
Requires-Python: >=3.7
License-File: LICENSE
Requires-Dist: ksupk
Requires-Dist: pillow
Dynamic: license-file
